esp32_manager/__init__.py
esp32_manager/cli.py
esp32_manager-1.0.1.dist-info/licenses/LICENSE
esp32_manager-1.0.1.dist-info/METADATA
esp32_manager-1.0.1.dist-info/WHEEL
esp32_manager-1.0.1.dist-info/entry_points.txt
esp32_manager-1.0.1.dist-info/top_level.txt
esp32_manager-1.0.1.dist-info/RECORD
