Metadata-Version: 2.4
Name: esp32-manager
Version: 1.0.1
Summary: A utility to manage files on an ESP32 running MicroPython.
Author-email: Juanmi Taboada <juanmi@juanmitaboada.com>
Classifier: Programming Language :: Python :: 3
Classifier: License :: OSI Approved :: MIT License
Classifier: Operating System :: OS Independent
Requires-Python: >=3.7
License-File: LICENSE
Requires-Dist: pyserial
Dynamic: license-file
